sealevelrise/__init__.py
sealevelrise/data.py
sealevelrise/historical.py
sealevelrise/noaaslr.py
sealevelrise/scenario.py
sealevelrise/slrprojections.py
sealevelrise/utils.py
sealevelrise/visualize.py
sealevelrise/data/scenarios.json
sealevelrise-0.1.1.dist-info/LICENSE
sealevelrise-0.1.1.dist-info/METADATA
sealevelrise-0.1.1.dist-info/WHEEL
sealevelrise-0.1.1.dist-info/top_level.txt
sealevelrise-0.1.1.dist-info/RECORD
