Metadata-Version: 2.1
Name: sealevelrise
Version: 0.1.1
Summary: Small utility for fetching, and manipulating Sea Level Rise Projections from various sources for engineering calculations
Home-page: https://github.com/jtoilliez/slr
Author: Jean O. Toilliez
Author-email: jeantoilliez@gmail.com
License: MIT
Project-URL: GitHub, https://github.com/jtoilliez/slr
Project-URL: PyPI, https://pypi.org/project/sealevelrise/
Keywords: sea level rise,climate,sustainability,NOAA,datums,water,risk,asset management,coastal,ocean,marine,environmental,engineering
Platform: UNKNOWN
Classifier: Programming Language :: Python :: 3
Classifier: License :: OSI Approved :: MIT License
Classifier: Intended Audience :: Science/Research
Classifier: Operating System :: OS Independent
Classifier: Topic :: Scientific/Engineering
Classifier: Topic :: Scientific/Engineering :: Hydrology
Requires-Python: >=3.9
License-File: LICENSE
Requires-Dist: numpy
Requires-Dist: pandas
Requires-Dist: matplotlib
Requires-Dist: pathlib
Provides-Extra: dev
Requires-Dist: pytest ; extra == 'dev'
Requires-Dist: pytest-cov ; extra == 'dev'
Requires-Dist: flake8 ; extra == 'dev'
Requires-Dist: jupyter ; extra == 'dev'
Requires-Dist: black ; extra == 'dev'
Requires-Dist: wheel ; extra == 'dev'
